transaction_counter.py
transaction_counter_annyandr-1.1.dist-info/METADATA
transaction_counter_annyandr-1.1.dist-info/WHEEL
transaction_counter_annyandr-1.1.dist-info/entry_points.txt
transaction_counter_annyandr-1.1.dist-info/top_level.txt
transaction_counter_annyandr-1.1.dist-info/RECORD
